{
  "ComponentIndexes": {},
  "ControlUniqueGuids": {},
  "ControlUniqueIds": {
    "AddMediaButton1": 204,
    "AddMediaWithImage1": 208,
    "Amenities": 66,
    "Amenities_2": 219,
    "Amenities_3": 310,
    "Amenities1": 123,
    "Amenities1_2": 268,
    "Amenities1_3": 359,
    "App": 1,
    "arrowDown": 54,
    "arrowDown_1": 59,
    "arrowDown_10": 217,
    "arrowDown_11": 222,
    "arrowDown_12": 308,
    "arrowDown_13": 313,
    "arrowDown_2": 64,
    "arrowDown_3": 69,
    "arrowUp": 55,
    "arrowUp_1": 60,
    "arrowUp_10": 218,
    "arrowUp_11": 223,
    "arrowUp_12": 309,
    "arrowUp_13": 314,
    "arrowUp_2": 65,
    "arrowUp_3": 70,
    "BasicDetails": 51,
    "BasicDetails_2": 211,
    "BasicDetails_3": 302,
    "BasicDetails1": 71,
    "BasicDetails1_2": 224,
    "BasicDetails1_3": 315,
    "BasicDetails2": 143,
    "BasicDetails2_2": 282,
    "BasicDetails2_3": 373,
    "Button1": 163,
    "Circle1": 179,
    "Circle1_1": 180,
    "Circle1_2": 181,
    "Circle1_3": 182,
    "ConstructionDetails": 56,
    "ConstructionDetails_2": 212,
    "ConstructionDetails_3": 303,
    "ConstructionDetails1": 87,
    "ConstructionDetails1_2": 236,
    "ConstructionDetails1_3": 327,
    "ConstructionDetails2": 103,
    "ConstructionDetails2_2": 246,
    "ConstructionDetails2_3": 337,
    "Container12": 192,
    "Container13": 190,
    "Container14": 191,
    "Container2": 5,
    "Container3": 34,
    "Container4": 52,
    "Container4_1": 57,
    "Container4_10": 215,
    "Container4_11": 220,
    "Container4_12": 304,
    "Container4_13": 306,
    "Container4_14": 311,
    "Container4_2": 62,
    "Container4_3": 67,
    "Container4_9": 213,
    "Container5": 161,
    "Container6": 162,
    "Container7": 72,
    "Container7_1": 88,
    "Container7_10": 225,
    "Container7_11": 237,
    "Container7_12": 247,
    "Container7_13": 253,
    "Container7_14": 269,
    "Container7_15": 316,
    "Container7_16": 328,
    "Container7_17": 338,
    "Container7_18": 344,
    "Container7_19": 360,
    "Container7_2": 104,
    "Container7_3": 112,
    "Container7_4": 124,
    "Container9": 144,
    "Container9_2": 283,
    "Container9_3": 374,
    "Dropdown2": 195,
    "Dropdown2_1": 197,
    "flter": 16,
    "galleryTemplate3": 33,
    "Group1": 205,
    "Group1_1": 206,
    "Group2": 207,
    "Header": 43,
    "Host": 3,
    "Icon2": 12,
    "Icon3": 18,
    "Icon4": 46,
    "Icon4_1": 165,
    "Icon4_2": 188,
    "Icon5": 183,
    "Image1": 9,
    "Image10": 49,
    "Image11": 131,
    "Image12": 42,
    "Image13": 130,
    "Image15": 128,
    "Image16": 127,
    "Image17": 125,
    "Image18": 138,
    "Image19": 142,
    "Image2": 7,
    "Image20": 141,
    "Image3": 13,
    "Image4": 35,
    "Image5": 14,
    "Image6": 17,
    "Image7": 134,
    "Image8": 40,
    "Image9": 133,
    "Img": 8,
    "KPI1": 20,
    "KPI2": 23,
    "KPI3": 26,
    "KPI4": 29,
    "KPIcontainer": 19,
    "Label1": 11,
    "Label10": 53,
    "Label10_1": 58,
    "Label10_10": 216,
    "Label10_11": 221,
    "Label10_12": 307,
    "Label10_13": 312,
    "Label10_2": 63,
    "Label10_3": 68,
    "Label11": 73,
    "Label11_1": 75,
    "Label11_10": 80,
    "Label11_11": 82,
    "Label11_118": 226,
    "Label11_119": 227,
    "Label11_12": 84,
    "Label11_120": 228,
    "Label11_121": 229,
    "Label11_122": 230,
    "Label11_123": 231,
    "Label11_124": 232,
    "Label11_125": 233,
    "Label11_126": 234,
    "Label11_127": 235,
    "Label11_128": 317,
    "Label11_129": 318,
    "Label11_13": 86,
    "Label11_130": 319,
    "Label11_131": 320,
    "Label11_132": 321,
    "Label11_133": 322,
    "Label11_134": 323,
    "Label11_135": 324,
    "Label11_136": 325,
    "Label11_137": 326,
    "Label11_14": 145,
    "Label11_15": 147,
    "Label11_16": 149,
    "Label11_17": 151,
    "Label11_18": 153,
    "Label11_180": 238,
    "Label11_181": 239,
    "Label11_182": 240,
    "Label11_183": 241,
    "Label11_184": 242,
    "Label11_185": 243,
    "Label11_186": 244,
    "Label11_187": 245,
    "Label11_188": 248,
    "Label11_189": 249,
    "Label11_19": 155,
    "Label11_190": 250,
    "Label11_191": 251,
    "Label11_192": 254,
    "Label11_193": 255,
    "Label11_194": 256,
    "Label11_195": 257,
    "Label11_196": 258,
    "Label11_197": 259,
    "Label11_198": 260,
    "Label11_199": 261,
    "Label11_2": 77,
    "Label11_20": 157,
    "Label11_200": 262,
    "Label11_201": 263,
    "Label11_202": 264,
    "Label11_203": 265,
    "Label11_204": 266,
    "Label11_205": 267,
    "Label11_206": 270,
    "Label11_207": 271,
    "Label11_208": 272,
    "Label11_209": 273,
    "Label11_21": 159,
    "Label11_210": 274,
    "Label11_211": 275,
    "Label11_212": 276,
    "Label11_213": 277,
    "Label11_214": 278,
    "Label11_215": 279,
    "Label11_216": 280,
    "Label11_217": 281,
    "Label11_218": 284,
    "Label11_219": 285,
    "Label11_22": 146,
    "Label11_220": 286,
    "Label11_221": 287,
    "Label11_222": 288,
    "Label11_223": 289,
    "Label11_224": 290,
    "Label11_225": 291,
    "Label11_226": 292,
    "Label11_227": 293,
    "Label11_228": 294,
    "Label11_229": 295,
    "Label11_23": 148,
    "Label11_230": 296,
    "Label11_231": 297,
    "Label11_232": 298,
    "Label11_233": 299,
    "Label11_234": 329,
    "Label11_235": 330,
    "Label11_236": 331,
    "Label11_237": 332,
    "Label11_238": 333,
    "Label11_239": 334,
    "Label11_24": 150,
    "Label11_240": 335,
    "Label11_241": 336,
    "Label11_242": 339,
    "Label11_243": 340,
    "Label11_244": 341,
    "Label11_245": 342,
    "Label11_246": 345,
    "Label11_247": 346,
    "Label11_248": 347,
    "Label11_249": 348,
    "Label11_25": 152,
    "Label11_250": 349,
    "Label11_251": 350,
    "Label11_252": 351,
    "Label11_253": 352,
    "Label11_254": 353,
    "Label11_255": 354,
    "Label11_256": 355,
    "Label11_257": 356,
    "Label11_258": 357,
    "Label11_259": 358,
    "Label11_26": 154,
    "Label11_260": 361,
    "Label11_261": 362,
    "Label11_262": 363,
    "Label11_263": 364,
    "Label11_264": 365,
    "Label11_265": 366,
    "Label11_266": 367,
    "Label11_267": 368,
    "Label11_268": 369,
    "Label11_269": 370,
    "Label11_27": 156,
    "Label11_270": 371,
    "Label11_271": 372,
    "Label11_272": 375,
    "Label11_273": 376,
    "Label11_274": 377,
    "Label11_275": 378,
    "Label11_276": 379,
    "Label11_277": 380,
    "Label11_278": 381,
    "Label11_279": 382,
    "Label11_28": 158,
    "Label11_280": 383,
    "Label11_281": 384,
    "Label11_282": 385,
    "Label11_283": 386,
    "Label11_284": 387,
    "Label11_285": 388,
    "Label11_286": 389,
    "Label11_287": 390,
    "Label11_29": 160,
    "Label11_3": 79,
    "Label11_30": 89,
    "Label11_31": 90,
    "Label11_32": 91,
    "Label11_33": 92,
    "Label11_34": 93,
    "Label11_35": 94,
    "Label11_36": 95,
    "Label11_37": 96,
    "Label11_38": 97,
    "Label11_39": 98,
    "Label11_4": 81,
    "Label11_40": 99,
    "Label11_41": 100,
    "Label11_42": 101,
    "Label11_43": 102,
    "Label11_44": 105,
    "Label11_45": 106,
    "Label11_46": 107,
    "Label11_47": 108,
    "Label11_48": 109,
    "Label11_49": 110,
    "Label11_5": 83,
    "Label11_58": 113,
    "Label11_59": 114,
    "Label11_6": 85,
    "Label11_60": 115,
    "Label11_61": 116,
    "Label11_62": 117,
    "Label11_63": 118,
    "Label11_64": 119,
    "Label11_65": 120,
    "Label11_66": 121,
    "Label11_67": 122,
    "Label11_7": 74,
    "Label11_73": 126,
    "Label11_75": 129,
    "Label11_77": 132,
    "Label11_79": 135,
    "Label11_8": 76,
    "Label11_81": 136,
    "Label11_83": 137,
    "Label11_84": 140,
    "Label11_85": 139,
    "Label11_9": 78,
    "Label12": 193,
    "Label13": 194,
    "Label13_1": 196,
    "Label13_2": 198,
    "Label13_3": 200,
    "Label13_4": 202,
    "Label2": 21,
    "Label2_1": 24,
    "Label2_2": 27,
    "Label2_3": 30,
    "Label3": 22,
    "Label3_1": 25,
    "Label3_2": 28,
    "Label3_3": 31,
    "Label5": 47,
    "Label5_1": 178,
    "Label5_2": 189,
    "Label6": 36,
    "Label7": 38,
    "Label8": 39,
    "Label8_1": 41,
    "Label9": 37,
    "OwnerDetails": 61,
    "OwnerDetails_2": 214,
    "OwnerDetails_3": 305,
    "OwnerDetails_4": 300,
    "OwnerDetails_5": 391,
    "OwnerDetails1": 111,
    "OwnerDetails1_2": 252,
    "OwnerDetails1_3": 343,
    "PropertyG": 50,
    "PropertyG_2": 210,
    "PropertyG_3": 301,
    "PropertyGrid": 32,
    "PropertyImage": 48,
    "Radio1": 201,
    "Rectangle1": 6,
    "Rectangle2_2": 185,
    "Rectangle2_3": 186,
    "Rectangle2_4": 184,
    "Screen1": 4,
    "Screen2": 10,
    "Screen3": 45,
    "Screen4": 164,
    "Screen5": 187,
    "Screen6": 209,
    "SearchInput": 44,
    "TextInput1": 15,
    "TextInput2": 199,
    "UploadedImage1": 203
  },
  "FunctionParamsInvariantScripts": {},
  "FunctionParamsInvariantScriptsOnInstances": {},
  "HeaderLastSavedDateTimeUTC": "12/08/2023 08:32:43",
  "IsLegacyComponentAllowGlobalScopeCase": false,
  "LocalConnectionIDReferences": {
    "61134af4-e3e3-4105-b4e1-e807bb4bf167": "\"/providers/microsoft.powerapps/apis/shared_sharepointonline/connections/832938808e0b419c8dc90fe74f425501\""
  },
  "LocalDatabaseReferencesAsEmpty": false,
  "LocalResourceFileNames": {
    "arrow-up": "0001.png",
    "avatar": "0002.png",
    "backup": "0003.png",
    "basketball-ball-variant": "0004.png",
    "clubhouse": "0005.png",
    "cricket-ground": "0006.png",
    "down-arrow (1)": "0007.png",
    "elliot-andrews-0Z_KzexdAH4-unsplash 1": "0008.png",
    "food-court": "0009.png",
    "Group 14": "0010.png",
    "Group 3": "0011.png",
    "location": "0012.png",
    "muscle": "0013.png",
    "park": "0014.png",
    "playground": "0015.png",
    "swimming": "0016.png",
    "tennis": "0017.png",
    "tie": "0018.png"
  },
  "LocalResourceRootPaths": {
    "arrow-up": "https://docserverpwaprodsin.blob.core.windows.net/ae0915b3-b22c-42f1-87ec-048ee0927d96-1/resource/Assets0Images00001.png?skoid=58690ece-ec83-4ce2-9ce8-883d4d6a54ee&sktid=975f013f-7f24-47e8-a7d3-abc4752bf346&skt=2023-12-08T08%3A30%3A16Z&ske=2023-12-09T08%3A45%3A16Z&sks=b&skv=2022-11-02&sv=2022-11-02&spr=https&se=2023-12-09T08%3A45%3A16Z&sr=b&sp=r&sig=nHFeWrQFAGGg8D9Duq0zbiRDwTjUimk%2BsVfzRo21Gjk%3D",
    "avatar": "https://docserverpwaprodsin.blob.core.windows.net/ae0915b3-b22c-42f1-87ec-048ee0927d96-1/resource/Assets0Images00002.png?skoid=58690ece-ec83-4ce2-9ce8-883d4d6a54ee&sktid=975f013f-7f24-47e8-a7d3-abc4752bf346&skt=2023-12-08T08%3A30%3A16Z&ske=2023-12-09T08%3A45%3A16Z&sks=b&skv=2022-11-02&sv=2022-11-02&spr=https&se=2023-12-09T08%3A45%3A16Z&sr=b&sp=r&sig=xQN17rGQKy%2FSA2tkyAwZWUNxnrlwHmo266ceiAjiTcI%3D",
    "backup": "https://docserverpwaprodsin.blob.core.windows.net/ae0915b3-b22c-42f1-87ec-048ee0927d96-1/resource/Assets0Images00003.png?skoid=58690ece-ec83-4ce2-9ce8-883d4d6a54ee&sktid=975f013f-7f24-47e8-a7d3-abc4752bf346&skt=2023-12-08T08%3A30%3A16Z&ske=2023-12-09T08%3A45%3A16Z&sks=b&skv=2022-11-02&sv=2022-11-02&spr=https&se=2023-12-09T08%3A45%3A16Z&sr=b&sp=r&sig=8%2FAJTaEYD%2B1Q%2FPdLDfiO9DFrz%2BFKN7ErBdyqGHqhSRQ%3D",
    "basketball-ball-variant": "https://docserverpwaprodsin.blob.core.windows.net/ae0915b3-b22c-42f1-87ec-048ee0927d96-1/resource/Assets0Images00004.png?skoid=58690ece-ec83-4ce2-9ce8-883d4d6a54ee&sktid=975f013f-7f24-47e8-a7d3-abc4752bf346&skt=2023-12-08T08%3A30%3A16Z&ske=2023-12-09T08%3A45%3A16Z&sks=b&skv=2022-11-02&sv=2022-11-02&spr=https&se=2023-12-09T08%3A45%3A16Z&sr=b&sp=r&sig=BCOzQI716DX%2BwU3RVB%2Fv4bt%2FuPpCpT6zCcHzk1%2FUjyA%3D",
    "clubhouse": "https://docserverpwaprodsin.blob.core.windows.net/ae0915b3-b22c-42f1-87ec-048ee0927d96-1/resource/Assets0Images00005.png?skoid=58690ece-ec83-4ce2-9ce8-883d4d6a54ee&sktid=975f013f-7f24-47e8-a7d3-abc4752bf346&skt=2023-12-08T08%3A30%3A16Z&ske=2023-12-09T08%3A45%3A16Z&sks=b&skv=2022-11-02&sv=2022-11-02&spr=https&se=2023-12-09T08%3A45%3A16Z&sr=b&sp=r&sig=W1voA8TEEyr7p%2BW7KziFAf8Tx3liO%2BeuRQuwSKbVF0E%3D",
    "cricket-ground": "https://docserverpwaprodsin.blob.core.windows.net/ae0915b3-b22c-42f1-87ec-048ee0927d96-1/resource/Assets0Images00006.png?skoid=58690ece-ec83-4ce2-9ce8-883d4d6a54ee&sktid=975f013f-7f24-47e8-a7d3-abc4752bf346&skt=2023-12-08T08%3A30%3A16Z&ske=2023-12-09T08%3A45%3A16Z&sks=b&skv=2022-11-02&sv=2022-11-02&spr=https&se=2023-12-09T08%3A45%3A16Z&sr=b&sp=r&sig=38vEcFaLAUkFg1Ny2lbwZgawDPPfZz9CKSxYi%2B8cPDo%3D",
    "down-arrow (1)": "https://docserverpwaprodsin.blob.core.windows.net/ae0915b3-b22c-42f1-87ec-048ee0927d96-1/resource/Assets0Images00007.png?skoid=58690ece-ec83-4ce2-9ce8-883d4d6a54ee&sktid=975f013f-7f24-47e8-a7d3-abc4752bf346&skt=2023-12-08T08%3A30%3A16Z&ske=2023-12-09T08%3A45%3A16Z&sks=b&skv=2022-11-02&sv=2022-11-02&spr=https&se=2023-12-09T08%3A45%3A16Z&sr=b&sp=r&sig=f0VZnbQ2eL8GVkHus%2Fg1q0epwRg8avPzWcACQOxUiv8%3D",
    "elliot-andrews-0Z_KzexdAH4-unsplash 1": "https://docserverpwaprodsin.blob.core.windows.net/ae0915b3-b22c-42f1-87ec-048ee0927d96-1/resource/Assets0Images00008.png?skoid=58690ece-ec83-4ce2-9ce8-883d4d6a54ee&sktid=975f013f-7f24-47e8-a7d3-abc4752bf346&skt=2023-12-08T08%3A30%3A16Z&ske=2023-12-09T08%3A45%3A16Z&sks=b&skv=2022-11-02&sv=2022-11-02&spr=https&se=2023-12-09T08%3A45%3A16Z&sr=b&sp=r&sig=QcxF5tKUGZ7a1iu1LtT43hWFBedK8A41TMQ6h20yJdY%3D",
    "food-court": "https://docserverpwaprodsin.blob.core.windows.net/ae0915b3-b22c-42f1-87ec-048ee0927d96-1/resource/Assets0Images00009.png?skoid=58690ece-ec83-4ce2-9ce8-883d4d6a54ee&sktid=975f013f-7f24-47e8-a7d3-abc4752bf346&skt=2023-12-08T08%3A30%3A16Z&ske=2023-12-09T08%3A45%3A16Z&sks=b&skv=2022-11-02&sv=2022-11-02&spr=https&se=2023-12-09T08%3A45%3A16Z&sr=b&sp=r&sig=jnDhyW5nNOtQRocjIxN%2Fn%2F6K7ldnR5HxJwdIzsM%2BryQ%3D",
    "Group 14": "https://docserverpwaprodsin.blob.core.windows.net/ae0915b3-b22c-42f1-87ec-048ee0927d96-1/resource/Assets0Images00010.png?skoid=58690ece-ec83-4ce2-9ce8-883d4d6a54ee&sktid=975f013f-7f24-47e8-a7d3-abc4752bf346&skt=2023-12-08T08%3A30%3A16Z&ske=2023-12-09T08%3A45%3A16Z&sks=b&skv=2022-11-02&sv=2022-11-02&spr=https&se=2023-12-09T08%3A45%3A16Z&sr=b&sp=r&sig=Xy%2Btm6ylDGRDrJJ%2BSk4%2BUM%2B9rVAyFXvvdCkmleeICf8%3D",
    "Group 3": "https://docserverpwaprodsin.blob.core.windows.net/ae0915b3-b22c-42f1-87ec-048ee0927d96-1/resource/Assets0Images00011.png?skoid=58690ece-ec83-4ce2-9ce8-883d4d6a54ee&sktid=975f013f-7f24-47e8-a7d3-abc4752bf346&skt=2023-12-08T08%3A30%3A16Z&ske=2023-12-09T08%3A45%3A16Z&sks=b&skv=2022-11-02&sv=2022-11-02&spr=https&se=2023-12-09T08%3A45%3A16Z&sr=b&sp=r&sig=yzHiVrmgkfS3P6gu6zLL%2BGZxPUVvc5hfBhZxDJVzECw%3D",
    "location": "https://docserverpwaprodsin.blob.core.windows.net/ae0915b3-b22c-42f1-87ec-048ee0927d96-1/resource/Assets0Images00012.png?skoid=58690ece-ec83-4ce2-9ce8-883d4d6a54ee&sktid=975f013f-7f24-47e8-a7d3-abc4752bf346&skt=2023-12-08T08%3A30%3A16Z&ske=2023-12-09T08%3A45%3A16Z&sks=b&skv=2022-11-02&sv=2022-11-02&spr=https&se=2023-12-09T08%3A45%3A16Z&sr=b&sp=r&sig=1kzdQwZFUel%2BN4KTSAvb4WU%2F74UjIdf%2BBn4dMnFh6eM%3D",
    "muscle": "https://docserverpwaprodsin.blob.core.windows.net/ae0915b3-b22c-42f1-87ec-048ee0927d96-1/resource/Assets0Images00013.png?skoid=58690ece-ec83-4ce2-9ce8-883d4d6a54ee&sktid=975f013f-7f24-47e8-a7d3-abc4752bf346&skt=2023-12-08T08%3A30%3A16Z&ske=2023-12-09T08%3A45%3A16Z&sks=b&skv=2022-11-02&sv=2022-11-02&spr=https&se=2023-12-09T08%3A45%3A16Z&sr=b&sp=r&sig=DEVHZihrixg7OCpUqDVz3f12DSz1EU95cy%2BC7LRU0h4%3D",
    "park": "https://docserverpwaprodsin.blob.core.windows.net/ae0915b3-b22c-42f1-87ec-048ee0927d96-1/resource/Assets0Images00014.png?skoid=58690ece-ec83-4ce2-9ce8-883d4d6a54ee&sktid=975f013f-7f24-47e8-a7d3-abc4752bf346&skt=2023-12-08T08%3A30%3A16Z&ske=2023-12-09T08%3A45%3A16Z&sks=b&skv=2022-11-02&sv=2022-11-02&spr=https&se=2023-12-09T08%3A45%3A16Z&sr=b&sp=r&sig=eTTH%2F63j2C37jeWUI0eoIJNO3B3gm0BDQfsQJPTNlXU%3D",
    "playground": "https://docserverpwaprodsin.blob.core.windows.net/ae0915b3-b22c-42f1-87ec-048ee0927d96-1/resource/Assets0Images00015.png?skoid=58690ece-ec83-4ce2-9ce8-883d4d6a54ee&sktid=975f013f-7f24-47e8-a7d3-abc4752bf346&skt=2023-12-08T08%3A30%3A16Z&ske=2023-12-09T08%3A45%3A16Z&sks=b&skv=2022-11-02&sv=2022-11-02&spr=https&se=2023-12-09T08%3A45%3A16Z&sr=b&sp=r&sig=y9EHeGI6I3Qtpd%2BUyGGPtCo6mRrqs8m9zY982%2BQ%2B6oU%3D",
    "swimming": "https://docserverpwaprodsin.blob.core.windows.net/ae0915b3-b22c-42f1-87ec-048ee0927d96-1/resource/Assets0Images00016.png?skoid=58690ece-ec83-4ce2-9ce8-883d4d6a54ee&sktid=975f013f-7f24-47e8-a7d3-abc4752bf346&skt=2023-12-08T08%3A30%3A16Z&ske=2023-12-09T08%3A45%3A16Z&sks=b&skv=2022-11-02&sv=2022-11-02&spr=https&se=2023-12-09T08%3A45%3A16Z&sr=b&sp=r&sig=auadatq51WkVcRjNsCO%2FuGq5c3yIU5fsNr4i7BTPs%2Fo%3D",
    "tennis": "https://docserverpwaprodsin.blob.core.windows.net/ae0915b3-b22c-42f1-87ec-048ee0927d96-1/resource/Assets0Images00017.png?skoid=58690ece-ec83-4ce2-9ce8-883d4d6a54ee&sktid=975f013f-7f24-47e8-a7d3-abc4752bf346&skt=2023-12-08T08%3A30%3A16Z&ske=2023-12-09T08%3A45%3A16Z&sks=b&skv=2022-11-02&sv=2022-11-02&spr=https&se=2023-12-09T08%3A45%3A16Z&sr=b&sp=r&sig=ZNtZkJ2k9m28L%2FwBp735NUTXyfmswmsYfzCmqUqSf9I%3D",
    "tie": "https://docserverpwaprodsin.blob.core.windows.net/ae0915b3-b22c-42f1-87ec-048ee0927d96-1/resource/Assets0Images00018.png?skoid=58690ece-ec83-4ce2-9ce8-883d4d6a54ee&sktid=975f013f-7f24-47e8-a7d3-abc4752bf346&skt=2023-12-08T08%3A30%3A16Z&ske=2023-12-09T08%3A45%3A16Z&sks=b&skv=2022-11-02&sv=2022-11-02&spr=https&se=2023-12-09T08%3A45%3A16Z&sr=b&sp=r&sig=x%2BJJs8xv2apNDypzuY4aqfJBWC%2FxkgP7oTc%2FhnPt%2B08%3D"
  },
  "OrderComponentMetadata": {},
  "OrderComponentTemplate": {},
  "OrderDataSource": {
    "colstages": 4,
    "currentData": 5,
    "CustomGallerySample": 0,
    "DropDownSample": 1,
    "GODREJ": 2,
    "RadioSample": 3,
    "Tabs": 6
  },
  "OrderGroupControls": {
    "AddMediaWithImage1": {
      "AddMediaButton1": 1,
      "UploadedImage1": 0
    },
    "Group1": {
      "Dropdown2": 0,
      "Label13": 1
    },
    "Group1_1": {
      "Dropdown2_1": 0,
      "Label13_1": 1
    },
    "Group2": {
      "Label13_2": 0,
      "TextInput2": 1
    },
    "Header": {
      "Icon2": 1,
      "Image3": 2,
      "Image5": 3,
      "Label1": 0
    },
    "SearchInput": {
      "Icon3": 1,
      "TextInput1": 0
    }
  },
  "OrderPcfTemplate": {},
  "OrderTemplate": {},
  "OrderXMLTemplate": {
    "addMedia": 11,
    "button": 7,
    "circle": 8,
    "dropdown": 9,
    "gallery": 6,
    "groupContainer": 0,
    "icon": 4,
    "image": 2,
    "label": 3,
    "radio": 10,
    "rectangle": 1,
    "text": 5
  },
  "OverridablePropertiesEntry": {
    "AddMediaButton1": {},
    "AddMediaWithImage1": {},
    "Amenities": {},
    "Amenities_2": {},
    "Amenities_3": {},
    "Amenities1": {},
    "Amenities1_2": {},
    "Amenities1_3": {},
    "App": {},
    "arrowDown": {},
    "arrowDown_1": {},
    "arrowDown_10": {},
    "arrowDown_11": {},
    "arrowDown_12": {},
    "arrowDown_13": {},
    "arrowDown_2": {},
    "arrowDown_3": {},
    "arrowUp": {},
    "arrowUp_1": {},
    "arrowUp_10": {},
    "arrowUp_11": {},
    "arrowUp_12": {},
    "arrowUp_13": {},
    "arrowUp_2": {},
    "arrowUp_3": {},
    "BasicDetails": {},
    "BasicDetails_2": {},
    "BasicDetails_3": {},
    "BasicDetails1": {},
    "BasicDetails1_2": {},
    "BasicDetails1_3": {},
    "BasicDetails2": {},
    "BasicDetails2_2": {},
    "BasicDetails2_3": {},
    "Button1": {},
    "Circle1": {},
    "Circle1_1": {},
    "Circle1_2": {},
    "Circle1_3": {},
    "ConstructionDetails": {},
    "ConstructionDetails_2": {},
    "ConstructionDetails_3": {},
    "ConstructionDetails1": {},
    "ConstructionDetails1_2": {},
    "ConstructionDetails1_3": {},
    "ConstructionDetails2": {},
    "ConstructionDetails2_2": {},
    "ConstructionDetails2_3": {},
    "Container12": {},
    "Container13": {},
    "Container14": {},
    "Container2": {},
    "Container3": {},
    "Container4": {},
    "Container4_1": {},
    "Container4_10": {},
    "Container4_11": {},
    "Container4_12": {},
    "Container4_13": {},
    "Container4_14": {},
    "Container4_2": {},
    "Container4_3": {},
    "Container4_9": {},
    "Container5": {},
    "Container6": {},
    "Container7": {},
    "Container7_1": {},
    "Container7_10": {},
    "Container7_11": {},
    "Container7_12": {},
    "Container7_13": {},
    "Container7_14": {},
    "Container7_15": {},
    "Container7_16": {},
    "Container7_17": {},
    "Container7_18": {},
    "Container7_19": {},
    "Container7_2": {},
    "Container7_3": {},
    "Container7_4": {},
    "Container9": {},
    "Container9_2": {},
    "Container9_3": {},
    "Dropdown2": {},
    "Dropdown2_1": {},
    "flter": {},
    "galleryTemplate3": {},
    "Group1": {},
    "Group1_1": {},
    "Group2": {},
    "Header": {},
    "Host": {},
    "Icon2": {},
    "Icon3": {},
    "Icon4": {},
    "Icon4_1": {},
    "Icon4_2": {},
    "Icon5": {},
    "Image1": {},
    "Image10": {},
    "Image11": {},
    "Image12": {},
    "Image13": {},
    "Image15": {},
    "Image16": {},
    "Image17": {},
    "Image18": {},
    "Image19": {},
    "Image2": {},
    "Image20": {},
    "Image3": {},
    "Image4": {},
    "Image5": {},
    "Image6": {},
    "Image7": {},
    "Image8": {},
    "Image9": {},
    "Img": {},
    "KPI1": {},
    "KPI2": {},
    "KPI3": {},
    "KPI4": {},
    "KPIcontainer": {},
    "Label1": {},
    "Label10": {},
    "Label10_1": {},
    "Label10_10": {},
    "Label10_11": {},
    "Label10_12": {},
    "Label10_13": {},
    "Label10_2": {},
    "Label10_3": {},
    "Label11": {},
    "Label11_1": {},
    "Label11_10": {},
    "Label11_11": {},
    "Label11_118": {},
    "Label11_119": {},
    "Label11_12": {},
    "Label11_120": {},
    "Label11_121": {},
    "Label11_122": {},
    "Label11_123": {},
    "Label11_124": {},
    "Label11_125": {},
    "Label11_126": {},
    "Label11_127": {},
    "Label11_128": {},
    "Label11_129": {},
    "Label11_13": {},
    "Label11_130": {},
    "Label11_131": {},
    "Label11_132": {},
    "Label11_133": {},
    "Label11_134": {},
    "Label11_135": {},
    "Label11_136": {},
    "Label11_137": {},
    "Label11_14": {},
    "Label11_15": {},
    "Label11_16": {},
    "Label11_17": {},
    "Label11_18": {},
    "Label11_180": {},
    "Label11_181": {},
    "Label11_182": {},
    "Label11_183": {},
    "Label11_184": {},
    "Label11_185": {},
    "Label11_186": {},
    "Label11_187": {},
    "Label11_188": {},
    "Label11_189": {},
    "Label11_19": {},
    "Label11_190": {},
    "Label11_191": {},
    "Label11_192": {},
    "Label11_193": {},
    "Label11_194": {},
    "Label11_195": {},
    "Label11_196": {},
    "Label11_197": {},
    "Label11_198": {},
    "Label11_199": {},
    "Label11_2": {},
    "Label11_20": {},
    "Label11_200": {},
    "Label11_201": {},
    "Label11_202": {},
    "Label11_203": {},
    "Label11_204": {},
    "Label11_205": {},
    "Label11_206": {},
    "Label11_207": {},
    "Label11_208": {},
    "Label11_209": {},
    "Label11_21": {},
    "Label11_210": {},
    "Label11_211": {},
    "Label11_212": {},
    "Label11_213": {},
    "Label11_214": {},
    "Label11_215": {},
    "Label11_216": {},
    "Label11_217": {},
    "Label11_218": {},
    "Label11_219": {},
    "Label11_22": {},
    "Label11_220": {},
    "Label11_221": {},
    "Label11_222": {},
    "Label11_223": {},
    "Label11_224": {},
    "Label11_225": {},
    "Label11_226": {},
    "Label11_227": {},
    "Label11_228": {},
    "Label11_229": {},
    "Label11_23": {},
    "Label11_230": {},
    "Label11_231": {},
    "Label11_232": {},
    "Label11_233": {},
    "Label11_234": {},
    "Label11_235": {},
    "Label11_236": {},
    "Label11_237": {},
    "Label11_238": {},
    "Label11_239": {},
    "Label11_24": {},
    "Label11_240": {},
    "Label11_241": {},
    "Label11_242": {},
    "Label11_243": {},
    "Label11_244": {},
    "Label11_245": {},
    "Label11_246": {},
    "Label11_247": {},
    "Label11_248": {},
    "Label11_249": {},
    "Label11_25": {},
    "Label11_250": {},
    "Label11_251": {},
    "Label11_252": {},
    "Label11_253": {},
    "Label11_254": {},
    "Label11_255": {},
    "Label11_256": {},
    "Label11_257": {},
    "Label11_258": {},
    "Label11_259": {},
    "Label11_26": {},
    "Label11_260": {},
    "Label11_261": {},
    "Label11_262": {},
    "Label11_263": {},
    "Label11_264": {},
    "Label11_265": {},
    "Label11_266": {},
    "Label11_267": {},
    "Label11_268": {},
    "Label11_269": {},
    "Label11_27": {},
    "Label11_270": {},
    "Label11_271": {},
    "Label11_272": {},
    "Label11_273": {},
    "Label11_274": {},
    "Label11_275": {},
    "Label11_276": {},
    "Label11_277": {},
    "Label11_278": {},
    "Label11_279": {},
    "Label11_28": {},
    "Label11_280": {},
    "Label11_281": {},
    "Label11_282": {},
    "Label11_283": {},
    "Label11_284": {},
    "Label11_285": {},
    "Label11_286": {},
    "Label11_287": {},
    "Label11_29": {},
    "Label11_3": {},
    "Label11_30": {},
    "Label11_31": {},
    "Label11_32": {},
    "Label11_33": {},
    "Label11_34": {},
    "Label11_35": {},
    "Label11_36": {},
    "Label11_37": {},
    "Label11_38": {},
    "Label11_39": {},
    "Label11_4": {},
    "Label11_40": {},
    "Label11_41": {},
    "Label11_42": {},
    "Label11_43": {},
    "Label11_44": {},
    "Label11_45": {},
    "Label11_46": {},
    "Label11_47": {},
    "Label11_48": {},
    "Label11_49": {},
    "Label11_5": {},
    "Label11_58": {},
    "Label11_59": {},
    "Label11_6": {},
    "Label11_60": {},
    "Label11_61": {},
    "Label11_62": {},
    "Label11_63": {},
    "Label11_64": {},
    "Label11_65": {},
    "Label11_66": {},
    "Label11_67": {},
    "Label11_7": {},
    "Label11_73": {},
    "Label11_75": {},
    "Label11_77": {},
    "Label11_79": {},
    "Label11_8": {},
    "Label11_81": {},
    "Label11_83": {},
    "Label11_84": {},
    "Label11_85": {},
    "Label11_9": {},
    "Label12": {},
    "Label13": {},
    "Label13_1": {},
    "Label13_2": {},
    "Label13_3": {},
    "Label13_4": {},
    "Label2": {},
    "Label2_1": {},
    "Label2_2": {},
    "Label2_3": {},
    "Label3": {},
    "Label3_1": {},
    "Label3_2": {},
    "Label3_3": {},
    "Label5": {},
    "Label5_1": {},
    "Label5_2": {},
    "Label6": {},
    "Label7": {},
    "Label8": {},
    "Label8_1": {},
    "Label9": {},
    "OwnerDetails": {},
    "OwnerDetails_2": {},
    "OwnerDetails_3": {},
    "OwnerDetails_4": {},
    "OwnerDetails_5": {},
    "OwnerDetails1": {},
    "OwnerDetails1_2": {},
    "OwnerDetails1_3": {},
    "PropertyG": {},
    "PropertyG_2": {},
    "PropertyG_3": {},
    "PropertyGrid": {},
    "PropertyImage": {},
    "Radio1": {},
    "Rectangle1": {},
    "Rectangle2_2": {},
    "Rectangle2_3": {},
    "Rectangle2_4": {},
    "Screen1": {},
    "Screen2": {},
    "Screen3": {},
    "Screen4": {},
    "Screen5": {},
    "Screen6": {},
    "SearchInput": {},
    "TextInput1": {},
    "TextInput2": {},
    "UploadedImage1": {}
  },
  "PCFDynamicSchemaForIRRetrievalEntry": {},
  "PCFTemplateEntry": {},
  "PublishOrderIndices": {
    "AddMediaButton1": 187,
    "AddMediaWithImage1": 185,
    "Amenities": 149,
    "Amenities_2": 259,
    "Amenities_3": 213,
    "Amenities1": 119,
    "Amenities1_2": 264,
    "Amenities1_3": 218,
    "App": 0,
    "arrowDown": 47,
    "arrowDown_1": 143,
    "arrowDown_10": 241,
    "arrowDown_11": 262,
    "arrowDown_12": 224,
    "arrowDown_13": 228,
    "arrowDown_2": 147,
    "arrowDown_3": 152,
    "arrowUp": 48,
    "arrowUp_1": 142,
    "arrowUp_10": 242,
    "arrowUp_11": 263,
    "arrowUp_12": 225,
    "arrowUp_13": 229,
    "arrowUp_2": 148,
    "arrowUp_3": 153,
    "BasicDetails": 44,
    "BasicDetails_2": 189,
    "BasicDetails_3": 210,
    "BasicDetails1": 49,
    "BasicDetails1_2": 190,
    "BasicDetails1_3": 214,
    "BasicDetails2": 65,
    "BasicDetails2_2": 202,
    "BasicDetails2_3": 219,
    "Button1": 156,
    "Circle1": 159,
    "Circle1_1": 160,
    "Circle1_2": 161,
    "Circle1_3": 162,
    "ConstructionDetails": 139,
    "ConstructionDetails_2": 236,
    "ConstructionDetails_3": 211,
    "ConstructionDetails1": 83,
    "ConstructionDetails1_2": 220,
    "ConstructionDetails1_3": 215,
    "ConstructionDetails2": 99,
    "ConstructionDetails2_2": 230,
    "ConstructionDetails2_3": 216,
    "Container12": 171,
    "Container13": 169,
    "Container14": 170,
    "Container2": 0,
    "Container3": 30,
    "Container4": 45,
    "Container4_1": 140,
    "Container4_10": 239,
    "Container4_11": 260,
    "Container4_12": 221,
    "Container4_13": 222,
    "Container4_14": 226,
    "Container4_2": 145,
    "Container4_3": 150,
    "Container4_9": 237,
    "Container5": 154,
    "Container6": 155,
    "Container7": 50,
    "Container7_1": 84,
    "Container7_10": 191,
    "Container7_11": 221,
    "Container7_12": 231,
    "Container7_13": 244,
    "Container7_14": 265,
    "Container7_15": 230,
    "Container7_16": 241,
    "Container7_17": 250,
    "Container7_18": 255,
    "Container7_19": 270,
    "Container7_2": 100,
    "Container7_3": 108,
    "Container7_4": 120,
    "Container9": 66,
    "Container9_2": 203,
    "Container9_3": 283,
    "Dropdown2": 175,
    "Dropdown2_1": 178,
    "flter": 12,
    "galleryTemplate3": 29,
    "Group1": 174,
    "Group1_1": 177,
    "Group2": 180,
    "Header": 6,
    "Host": 0,
    "Icon2": 8,
    "Icon3": 14,
    "Icon4": 39,
    "Icon4_1": 157,
    "Icon4_2": 167,
    "Icon5": 163,
    "Image1": 4,
    "Image10": 42,
    "Image11": 125,
    "Image12": 38,
    "Image13": 126,
    "Image15": 130,
    "Image16": 134,
    "Image17": 129,
    "Image18": 133,
    "Image19": 138,
    "Image2": 2,
    "Image20": 137,
    "Image3": 9,
    "Image4": 31,
    "Image5": 10,
    "Image6": 13,
    "Image7": 121,
    "Image8": 36,
    "Image9": 122,
    "Img": 3,
    "KPI1": 16,
    "KPI2": 19,
    "KPI3": 22,
    "KPI4": 25,
    "KPIcontainer": 15,
    "Label1": 5,
    "Label10": 46,
    "Label10_1": 141,
    "Label10_10": 240,
    "Label10_11": 261,
    "Label10_12": 223,
    "Label10_13": 227,
    "Label10_2": 146,
    "Label10_3": 151,
    "Label11": 51,
    "Label11_1": 53,
    "Label11_10": 58,
    "Label11_11": 60,
    "Label11_118": 192,
    "Label11_119": 193,
    "Label11_12": 62,
    "Label11_120": 194,
    "Label11_121": 195,
    "Label11_122": 196,
    "Label11_123": 197,
    "Label11_124": 198,
    "Label11_125": 199,
    "Label11_126": 200,
    "Label11_127": 201,
    "Label11_128": 231,
    "Label11_129": 232,
    "Label11_13": 64,
    "Label11_130": 233,
    "Label11_131": 234,
    "Label11_132": 235,
    "Label11_133": 236,
    "Label11_134": 237,
    "Label11_135": 238,
    "Label11_136": 239,
    "Label11_137": 240,
    "Label11_14": 67,
    "Label11_15": 69,
    "Label11_16": 71,
    "Label11_17": 73,
    "Label11_18": 75,
    "Label11_180": 222,
    "Label11_181": 223,
    "Label11_182": 224,
    "Label11_183": 225,
    "Label11_184": 226,
    "Label11_185": 227,
    "Label11_186": 228,
    "Label11_187": 229,
    "Label11_188": 232,
    "Label11_189": 233,
    "Label11_19": 77,
    "Label11_190": 234,
    "Label11_191": 235,
    "Label11_192": 245,
    "Label11_193": 246,
    "Label11_194": 247,
    "Label11_195": 248,
    "Label11_196": 249,
    "Label11_197": 250,
    "Label11_198": 251,
    "Label11_199": 252,
    "Label11_2": 55,
    "Label11_20": 79,
    "Label11_200": 253,
    "Label11_201": 254,
    "Label11_202": 255,
    "Label11_203": 256,
    "Label11_204": 257,
    "Label11_205": 258,
    "Label11_206": 267,
    "Label11_207": 266,
    "Label11_208": 268,
    "Label11_209": 269,
    "Label11_21": 81,
    "Label11_210": 270,
    "Label11_211": 271,
    "Label11_212": 272,
    "Label11_213": 273,
    "Label11_214": 274,
    "Label11_215": 275,
    "Label11_216": 276,
    "Label11_217": 277,
    "Label11_218": 204,
    "Label11_219": 205,
    "Label11_22": 68,
    "Label11_220": 206,
    "Label11_221": 207,
    "Label11_222": 208,
    "Label11_223": 209,
    "Label11_224": 210,
    "Label11_225": 211,
    "Label11_226": 212,
    "Label11_227": 213,
    "Label11_228": 214,
    "Label11_229": 215,
    "Label11_23": 70,
    "Label11_230": 216,
    "Label11_231": 217,
    "Label11_232": 218,
    "Label11_233": 219,
    "Label11_234": 242,
    "Label11_235": 243,
    "Label11_236": 244,
    "Label11_237": 245,
    "Label11_238": 246,
    "Label11_239": 247,
    "Label11_24": 72,
    "Label11_240": 248,
    "Label11_241": 249,
    "Label11_242": 251,
    "Label11_243": 252,
    "Label11_244": 253,
    "Label11_245": 254,
    "Label11_246": 256,
    "Label11_247": 257,
    "Label11_248": 258,
    "Label11_249": 259,
    "Label11_25": 74,
    "Label11_250": 260,
    "Label11_251": 261,
    "Label11_252": 262,
    "Label11_253": 263,
    "Label11_254": 264,
    "Label11_255": 265,
    "Label11_256": 266,
    "Label11_257": 267,
    "Label11_258": 268,
    "Label11_259": 269,
    "Label11_26": 76,
    "Label11_260": 271,
    "Label11_261": 272,
    "Label11_262": 273,
    "Label11_263": 274,
    "Label11_264": 275,
    "Label11_265": 276,
    "Label11_266": 277,
    "Label11_267": 278,
    "Label11_268": 279,
    "Label11_269": 280,
    "Label11_27": 78,
    "Label11_270": 281,
    "Label11_271": 282,
    "Label11_272": 284,
    "Label11_273": 285,
    "Label11_274": 286,
    "Label11_275": 287,
    "Label11_276": 288,
    "Label11_277": 289,
    "Label11_278": 290,
    "Label11_279": 291,
    "Label11_28": 80,
    "Label11_280": 292,
    "Label11_281": 293,
    "Label11_282": 294,
    "Label11_283": 295,
    "Label11_284": 296,
    "Label11_285": 297,
    "Label11_286": 298,
    "Label11_287": 299,
    "Label11_29": 82,
    "Label11_3": 57,
    "Label11_30": 85,
    "Label11_31": 86,
    "Label11_32": 87,
    "Label11_33": 88,
    "Label11_34": 89,
    "Label11_35": 90,
    "Label11_36": 91,
    "Label11_37": 92,
    "Label11_38": 93,
    "Label11_39": 94,
    "Label11_4": 59,
    "Label11_40": 95,
    "Label11_41": 96,
    "Label11_42": 97,
    "Label11_43": 98,
    "Label11_44": 101,
    "Label11_45": 102,
    "Label11_46": 103,
    "Label11_47": 104,
    "Label11_48": 105,
    "Label11_49": 106,
    "Label11_5": 61,
    "Label11_58": 109,
    "Label11_59": 110,
    "Label11_6": 63,
    "Label11_60": 111,
    "Label11_61": 112,
    "Label11_62": 113,
    "Label11_63": 114,
    "Label11_64": 115,
    "Label11_65": 116,
    "Label11_66": 117,
    "Label11_67": 118,
    "Label11_7": 52,
    "Label11_73": 123,
    "Label11_75": 124,
    "Label11_77": 127,
    "Label11_79": 128,
    "Label11_8": 54,
    "Label11_81": 131,
    "Label11_83": 135,
    "Label11_84": 136,
    "Label11_85": 132,
    "Label11_9": 56,
    "Label12": 172,
    "Label13": 173,
    "Label13_1": 176,
    "Label13_2": 179,
    "Label13_3": 182,
    "Label13_4": 184,
    "Label2": 17,
    "Label2_1": 20,
    "Label2_2": 23,
    "Label2_3": 26,
    "Label3": 18,
    "Label3_1": 21,
    "Label3_2": 24,
    "Label3_3": 27,
    "Label5": 40,
    "Label5_1": 158,
    "Label5_2": 168,
    "Label6": 32,
    "Label7": 34,
    "Label8": 35,
    "Label8_1": 37,
    "Label9": 33,
    "OwnerDetails": 144,
    "OwnerDetails_2": 238,
    "OwnerDetails_3": 212,
    "OwnerDetails_4": 278,
    "OwnerDetails_5": 220,
    "OwnerDetails1": 107,
    "OwnerDetails1_2": 243,
    "OwnerDetails1_3": 217,
    "PropertyG": 43,
    "PropertyG_2": 188,
    "PropertyG_3": 209,
    "PropertyGrid": 28,
    "PropertyImage": 41,
    "Radio1": 183,
    "Rectangle1": 1,
    "Rectangle2_2": 165,
    "Rectangle2_3": 166,
    "Rectangle2_4": 164,
    "Screen1": 3,
    "Screen2": 9,
    "Screen3": 44,
    "Screen4": 163,
    "Screen5": 186,
    "Screen6": 208,
    "SearchInput": 7,
    "TextInput1": 11,
    "TextInput2": 181,
    "UploadedImage1": 186
  },
  "ResourcesJsonIndices": {
    "Image-arrow-up": 1,
    "Image-avatar": 2,
    "Image-backup": 3,
    "Image-basketball-ball-variant": 4,
    "Image-clubhouse": 5,
    "Image-cricket-ground": 6,
    "Image-down-arrow (1)": 7,
    "Image-elliot-andrews-0Z_KzexdAH4-unsplash 1": 8,
    "Image-food-court": 9,
    "Image-Group 14": 10,
    "Image-Group 3": 11,
    "Image-location": 12,
    "Image-muscle": 13,
    "Image-park": 14,
    "Image-playground": 15,
    "Image-SampleImage": 0,
    "Image-swimming": 16,
    "Image-tennis": 17,
    "Image-tie": 18
  },
  "RuleScreenIdWithoutScreen": {},
  "TemplateVersions": {},
  "VolatileProperties": {
    "AnalysisLoadTime": 1.4284457,
    "ControlCount": {
      "addMedia": 1,
      "button": 1,
      "circle": 4,
      "dropdown": 2,
      "gallery": 1,
      "galleryTemplate": 1,
      "group": 6,
      "groupContainer": 90,
      "icon": 6,
      "image": 36,
      "label": 227,
      "radio": 1,
      "rectangle": 4,
      "screen": 6,
      "text": 2
    },
    "DeserializationLoadTime": 2.5437429
  },
  "WasLocalDatabaseReferencesEmpty": true
}